{
    "version": 3,
    "cmakeMinimumRequired": {
      "major": 3,
      "minor": 21,
      "patch": 0
    },
    "configurePresets": [
      {
          "name": "Base",
          "hidden": true,
          "binaryDir": "${sourceDir}/build/${presetName}",
          "installDir": "${sourceDir}/install/${presetName}",
          "cacheVariables": {
              "NC_INSTALL_DIR": "${sourceDir}/../install"
          }
      },
      {
          "name": "Release-Base",
          "hidden": true,
          "inherits": [ "Base" ],
          "cacheVariables": {
              "CMAKE_BUILD_TYPE": "Release"
          }
      },
      {
        "name": "Debug-Base",
        "hidden": true,
        "inherits": [ "Base" ],
        "cacheVariables": {
            "CMAKE_BUILD_TYPE": "Debug",
            "NC_EDITOR_ENABLED": "ON",
            "NC_DEBUG_RENDERING": "ON",
            "NC_TESTS_ENABLED": "ON",
            "VERBOSE_LOGGING_ENABLED": "ON"
        }
      },
      {
        "name": "MSVC-Base",
        "hidden": true,
        "generator": "Visual Studio 17 2022"
      },
      {
        "name": "Ninja-Base",
        "hidden": true,
        "generator": "Ninja"
      },
      {
        "name": "Sample-MSVC-Release",
        "inherits": [ "Release-Base", "MSVC-Base" ],
        "cacheVariables": {
          "NC_BUILD_TYPE": "${presetName}",
          "NC_INSTALL_DIR": "${sourceDir}/../install/NcEngine/NcEngine-MSVC-Release"
        }
      },
      {
        "name": "Sample-Ninja-Release",
        "inherits": [ "Release-Base", "Ninja-Base" ],
        "cacheVariables": {
          "NC_BUILD_TYPE": "${presetName}",
          "NC_INSTALL_DIR": "${sourceDir}/../install/NcEngine/NcEngine-Ninja-Release"
        }
      },
       {
         "name": "Sample-MSVC-Debug",
         "inherits": [ "Debug-Base", "MSVC-Base" ],
         "cacheVariables": {
           "NC_BUILD_TYPE": "${presetName}",
           "NC_INSTALL_DIR": "${sourceDir}/../install/NcEngine/NcEngine-MSVC-Debug"
         }
       },
       {
         "name": "Sample-Ninja-Debug",
         "inherits": [ "Debug-Base", "Ninja-Base" ],
         "cacheVariables": {
           "NC_BUILD_TYPE": "${presetName}",
           "NC_INSTALL_DIR": "${sourceDir}/../install/NcEngine/NcEngine-Ninja-Debug"
         }
       },
       {
         "name": "Sample-MSVC-Debug-WithValidation",
         "inherits": [ "Debug-Base", "MSVC-Base" ],
         "cacheVariables": {
           "NC_BUILD_TYPE": "${presetName}",
           "NC_INSTALL_DIR": "${sourceDir}/../install/NcEngine/NcEngine-MSVC-Debug-WithValidation",
           "NC_USE_VALIDATION": "ON"
         }
       },
       {
         "name": "Sample-Ninja-Debug-WithValidation",
         "inherits": [ "Debug-Base", "Ninja-Base" ],
         "cacheVariables": {
           "NC_BUILD_TYPE": "${presetName}",
           "NC_INSTALL_DIR": "${sourceDir}/../install/NcEngine/NcEngine-Ninja-Debug-WithValidation",
           "NC_USE_VALIDATION": "ON"
         }
       },
       {
         "name": "Sample-MSVC-Release-WithEditor",
         "inherits": [ "Debug-Base", "MSVC-Base" ],
         "cacheVariables": {
           "NC_BUILD_TYPE": "${presetName}",
           "NC_INSTALL_DIR": "${sourceDir}/../install/NcEngine/NcEngine-MSVC-Release-WithEditor",
           "NC_EDITOR_ENABLED": "ON"
         }
       },
      {
        "name": "Sample-Ninja-Release-WithEditor",
        "inherits": [ "Debug-Base", "Ninja-Base" ],
        "cacheVariables": {
          "NC_BUILD_TYPE": "${presetName}",
          "NC_INSTALL_DIR": "${sourceDir}/../install/NcEngine/NcEngine-Ninja-Release-WithEditor",
          "NC_EDITOR_ENABLED": "ON"
        }
      },
      {
        "name": "Sample-MSVC-Release-WithProfiling",
        "inherits": [ "Debug-Base", "MSVC-Base" ],
        "cacheVariables": {
          "NC_BUILD_TYPE": "${presetName}",
          "NC_INSTALL_DIR": "${sourceDir}/../install/NcEngine/NcEngine-MSVC-Release-WithProfiling",
          "NC_PROFILING_ENABLED": "ON"
        }
      },
      {
        "name": "Sample-Ninja-Release-WithProfiling",
        "inherits": [ "Debug-Base", "Ninja-Base" ],
        "cacheVariables": {
          "NC_BUILD_TYPE": "${presetName}",
          "NC_INSTALL_DIR": "${sourceDir}/../install/NcEngine/NcEngine-Ninja-Release-WithProfiling",
          "NC_PROFILING_ENABLED": "ON"
        }
      },
       {
         "name": "Sample-MSVC-Release-WithValidation",
         "inherits": [ "Debug-Base", "MSVC-Base" ],
         "cacheVariables": {
           "NC_BUILD_TYPE": "${presetName}",
           "NC_INSTALL_DIR": "${sourceDir}/../install/NcEngine/NcEngine-MSVC-Release-WithValidation",
           "NC_EDITOR_ENABLED": "ON",
           "NC_DEBUG_RENDERING": "ON",
           "NC_USE_VALIDATION": "ON"
         }
       },
       {
         "name": "Sample-Ninja-Release-WithValidation",
         "inherits": [ "Debug-Base", "Ninja-Base" ],
         "cacheVariables": {
           "NC_BUILD_TYPE": "${presetName}",
           "NC_INSTALL_DIR": "${sourceDir}/../install/NcEngine/NcEngine-Ninja-Release-WithValidation",
           "NC_EDITOR_ENABLED": "ON",
           "NC_DEBUG_RENDERING": "ON",
           "NC_USE_VALIDATION": "ON"
         }
       }
    ],
  "buildPresets": [
    {
      "name": "Sample-MSVC-Release",
      "configurePreset": "Sample-MSVC-Release"
    },
    {
      "name": "Sample-Ninja-Release",
      "configurePreset": "Sample-Ninja-Release"
    },
    {
      "name": "Sample-MSVC-Debug",
      "configurePreset": "Sample-MSVC-Debug"
    },
    {
      "name": "Sample-Ninja-Debug",
      "configurePreset": "Sample-Ninja-Debug"
    },
    {
      "name": "Sample-MSVC-Debug-WithValidation",
      "configurePreset": "Sample-MSVC-Debug-WithValidation"
    },
    {
      "name": "Sample-Ninja-Debug-WithValidation",
      "configurePreset": "Sample-Ninja-Debug-WithValidation"
    },
    {
      "name": "Sample-MSVC-Release-WithEditor",
      "configurePreset": "Sample-MSVC-Release-WithEditor"
    },
    {
      "name": "Sample-Ninja-Release-WithEditor",
      "configurePreset": "Sample-Ninja-Release-WithEditor"
    },
    {
      "name": "Sample-MSVC-Release-WithProfiling",
      "configurePreset": "Sample-MSVC-Release-WithProfiling"
    },
    {
      "name": "Sample-Ninja-Release-WithProfiling",
      "configurePreset": "Sample-Ninja-Release-WithProfiling"
    },
    {
      "name": "Sample-MSVC-Release-WithValidation",
      "configurePreset": "Sample-MSVC-Release-WithValidation"
    },
    {
      "name": "Sample-Ninja-Release-WithValidation",
      "configurePreset": "Sample-Ninja-Release-WithValidation"
    }
  ]
}